widgitutils/__init__.py
widgitutils/color.py
widgitutils/embeds.py
widgitutils/format.py
widgitutils-0.0.12.dist-info/LICENSE
widgitutils-0.0.12.dist-info/METADATA
widgitutils-0.0.12.dist-info/WHEEL
widgitutils-0.0.12.dist-info/top_level.txt
widgitutils-0.0.12.dist-info/RECORD
