Metadata-Version: 2.1
Name: widgitutils
Version: 0.0.12
Summary: A suite of common-use utilities for our cogs.
Home-page: https://gitlab.com/widgitlabs/widgitutils
Author: Widgit Labs
License: MIT
Project-URL: Issue tracker, https://gitlab.com/widgitlabs/widgitutils/issues
Platform: UNKNOWN
Classifier: Development Status :: 5 - Production/Stable
Classifier: License :: OSI Approved :: MIT License
Classifier: Intended Audience :: Developers
Classifier: Natural Language :: English
Classifier: Operating System :: OS Independent
Classifier: Programming Language :: Python :: 3.5
Classifier: Programming Language :: Python :: 3.6
Classifier: Programming Language :: Python :: 3.7
Classifier: Programming Language :: Python :: 3.8
Classifier: Topic :: Software Development :: Libraries
Classifier: Topic :: Software Development :: Libraries :: Python Modules
Classifier: Topic :: Utilities
Requires-Python: >=3.5.3
Requires-Dist: red-discordbot
